<?xml version="1.0" encoding="utf-8"?>
<Entity parent="template_structure_camp">
  <BuildRestrictions>
    <Category>Storehouse</Category>
    <Territory>own neutral</Territory>
  </BuildRestrictions>
  <Cost>
    <BuildTime>35</BuildTime>
    <Resources>
      <metal>125</metal>
    </Resources>
  </Cost>
  <Footprint>
    <Circle radius="18.0"/>
    <Height>10.0</Height>
  </Footprint>
  <Health>
    <Max>1000</Max>
    <SpawnEntityOnDeath>rubble/debris_ordona_plantationA</SpawnEntityOnDeath>
    <SpawnMultipleEntitiesOnDeath>
      <Chance>100</Chance>
      <SpawnNumberMax>1</SpawnNumberMax>
      <SpawnNumberMin>1</SpawnNumberMin>
      <Template>structures/node_campA</Template>
    </SpawnMultipleEntitiesOnDeath>
  </Health>
  <Identity>
    <Civ>ordona</Civ>
    <Classes datatype="tokens">Village DropsiteFood DropsiteWood DropsiteMetal DropsiteStone</Classes>
    <GenericName>Plantation</GenericName>
    <History>Plantations were devoted entirely to the production of excess and surpluss food stocks. A lone Plantation could provide quite a feast for its entire population after its crops had grown.</History>
    <Icon>structures/ordona/ord_plantation.dds</Icon>
    <Tooltip>Center of an Ordonian Camp. Automatically generates Rupees.</Tooltip>
    <VisibleClasses datatype="tokens">Storehouse</VisibleClasses>
  </Identity>
  <Obstruction>
    <Static depth="20.0" width="20.0"/>
  </Obstruction>
  <Plots>
    <PlotsToSpawn>
      <TowerA>
        <Angle>-25</Angle>
        <LinkedDestruction>true</LinkedDestruction>
        <Template>structures/ordona/ordona_plot_tower</Template>
        <X>-27</X>
        <Z>47</Z>
      </TowerA>
      <TowerB>
        <Angle>155</Angle>
        <LinkedDestruction>true</LinkedDestruction>
        <Template>structures/ordona/ordona_plot_tower</Template>
        <X>27</X>
        <Z>-47</Z>
      </TowerB>
      <FenceA>
        <Angle>7</Angle>
        <LinkedDestruction>true</LinkedDestruction>
        <Template>gaia/doodads/ordona_fenceB</Template>
        <X>7</X>
        <Z>50</Z>
      </FenceA>
      <FenceB>
        <Angle>90</Angle>
        <LinkedDestruction>true</LinkedDestruction>
        <Template>gaia/doodads/ordona_fenceB</Template>
        <X>50</X>
        <Z>0</Z>
      </FenceB>
      <FenceC>
        <Angle>190</Angle>
        <LinkedDestruction>true</LinkedDestruction>
        <Template>gaia/doodads/ordona_fenceB</Template>
        <X>-7</X>
        <Z>-50</Z>
      </FenceC>
      <FenceD>
        <Angle>270</Angle>
        <LinkedDestruction>true</LinkedDestruction>
        <Template>gaia/doodads/ordona_fenceB</Template>
        <X>-50</X>
        <Z>0</Z>
      </FenceD>
      <TreeA>
        <Angle>-35</Angle>
        <LinkedDestruction>true</LinkedDestruction>
        <Template>gaia/tree_decor/ordona_treeA_decor</Template>
        <X>45</X>
        <Z>30</Z>
      </TreeA>
      <TreeB>
        <Angle>135</Angle>
        <LinkedDestruction>true</LinkedDestruction>
        <Template>gaia/tree_decor/ordona_treeA_decor</Template>
        <X>-45</X>
        <Z>-30</Z>
      </TreeB>
      <TreeC>
        <Angle>-35</Angle>
        <LinkedDestruction>true</LinkedDestruction>
        <Template>gaia/tree_decor/ordona_treeA_decor</Template>
        <X>-45</X>
        <Z>30</Z>
      </TreeC>
      <TreeD>
        <Angle>135</Angle>
        <LinkedDestruction>true</LinkedDestruction>
        <Template>gaia/tree_decor/ordona_treeA_decor</Template>
        <X>45</X>
        <Z>-30</Z>
      </TreeD>
    </PlotsToSpawn>
  </Plots>
  <RallyPoint disable=""/>
  <Researcher>
    <Technologies datatype="tokens">
    </Technologies>
  </Researcher>
  <Resistance>
    <Entity>
      <Damage>
        <Crush>40.0</Crush>
        <Hack>50.0</Hack>
        <Pierce>95.0</Pierce>
      </Damage>
    </Entity>
    <Foundation>
      <Damage>
        <Crush>1</Crush>
        <Fire>0.0</Fire>
        <Forest>0.0</Forest>
        <Hack>1</Hack>
        <Light>0.0</Light>
        <Pierce>95</Pierce>
        <Shadow>0.0</Shadow>
        <Siege>0.0</Siege>
        <Spirit>0.0</Spirit>
        <Water>0.0</Water>
      </Damage>
    </Foundation>
  </Resistance>
  <ResourceDrain>
    <MaxResourceSpotsToDrainSimultaneously>
      <metal.fruit>3</metal.fruit>
      <metal.fish>3</metal.fish>
      <metal.grain>3</metal.grain>
      <metal.tree>3</metal.tree>
      <metal.rock>1</metal.rock>
      <metal.ore>1</metal.ore>
      <metal.rupees>1</metal.rupees>
      <metal.gold>1</metal.gold>
      <metal.forcegems>1</metal.forcegems>
    </MaxResourceSpotsToDrainSimultaneously>
    <Radius>100</Radius>
    <ResourcesPerTick>
      <metal.fruit>1</metal.fruit>
      <metal.fish>1</metal.fish>
      <metal.grain>1</metal.grain>
      <metal.tree>1</metal.tree>
      <metal.rock>1</metal.rock>
      <metal.ore>1</metal.ore>
      <metal.rupees>1</metal.rupees>
      <metal.gold>1</metal.gold>
      <metal.forcegems>1</metal.forcegems>
    </ResourcesPerTick>
    <TickRate>2000</TickRate>
    <VisualEffectDuration>1000</VisualEffectDuration>
  </ResourceDrain>
  <ResourceDropsite>
    <Sharable>true</Sharable>
    <Types>metal</Types>
  </ResourceDropsite>
  <ResourceTrickle>
    <Interval>2000</Interval>
    <Rates>
      
    </Rates>
  </ResourceTrickle>
  <Sound>
    <SoundGroups>
      <constructed>interface/complete/building/complete_farm.xml</constructed>
      <select>interface/select/building/sel_farm.xml</select>
    </SoundGroups>
  </Sound>
  <TerritoryInfluence>
    <Radius>75</Radius>
    <Root>true</Root>
    <Weight>30000</Weight>
  </TerritoryInfluence>
  <Trainer>
    <BatchTimeModifier>0.8</BatchTimeModifier>
  </Trainer>
  <Vision>
    <Range>20</Range>
  </Vision>
  <VisualActor>
    <Actor>structures/ordona/ordona_plantationA.xml</Actor>
    <FoundationActor>structures/ordona/ordona_scaffoldB.xml</FoundationActor>
  </VisualActor>
</Entity>
