<?xml version="1.0" encoding="utf-8"?>
<Entity parent="template_structure_military_fortress">
  <Attack>
    <Ranged>
      <AttackName>Crossbow Bolt</AttackName>
      <Damage>
        <Pierce>15.0</Pierce>
      </Damage>
      <MaxRange>140.0</MaxRange>
      <MinRange>0.0</MinRange>
      <Origin>
        <X>0</X>
        <Y>15</Y>
        <Z>0</Z>
      </Origin>
      <PreferredClasses datatype="tokens">Human</PreferredClasses>
      <PrepareTime>1200</PrepareTime>
      <Projectile>
        <FriendlyFire>false</FriendlyFire>
        <Gravity>9.81</Gravity>
        <LaunchPoint y="3"/>
        <Speed>75.0</Speed>
        <Spread>1.5</Spread>
      </Projectile>
      <RepeatTime>2000</RepeatTime>
    </Ranged>
  </Attack>
  <BuildingAI>
    <DefaultArrowCount>10</DefaultArrowCount>
    <GarrisonArrowClasses>Infantry</GarrisonArrowClasses>
    <GarrisonArrowMultiplier>1</GarrisonArrowMultiplier>
  </BuildingAI>
  <Cost>
    <BuildTime>120</BuildTime>
    <Resources>
      <food>0</food>
      <wood>750</wood>
      <stone>0</stone>
      <metal>0</metal>
    </Resources>
  </Cost>
  <Footprint replace="">
    <Circle radius="30.0"/>
    <Height>45.0</Height>
  </Footprint>
  <Health>
    <Max>8000</Max>
    <SpawnEntityOnDeath>decay|rubble/debris_ordona_garrisonA</SpawnEntityOnDeath>
  </Health>
  <Identity>
    <Civ>deku</Civ>
    <SpecificName>Ranger Garrison</SpecificName>
    <History>A wooden fort that is sometimes found on the borders of the Province where raids from Moblins and Lizalfos often approach. Ordonian Rangers often use these forts as bases of operation, and young rangers are raised and trained here.</History>
    <Icon>structures/ordona/ord_rangergarrison.dds</Icon>
    <Tooltip>Giant Defense fortification that attacks many enemies and generates Territory. Can also train Rangers.</Tooltip>
  </Identity>
  <Obstruction>
    <Static width="55.0" depth="55.0"/>
  </Obstruction>
  <Population>
    <Bonus>10</Bonus>
  </Population>
  <Sound>
    <SoundGroups>
      <attack_ranged>attack/natural/dekuscrub_spit.xml</attack_ranged>
    </SoundGroups>
  </Sound>
  <Trainer>
    <BatchTimeModifier>0.8</BatchTimeModifier>
    <Entities datatype="tokens">
      units/ordona/ordona_ranger_b
    </Entities>
  </Trainer>
  <TurretHolder>
    <TurretPoints>
      <Archer1>
        <X>17.6</X>
        <Y>21.9</Y>
        <Z>0</Z>
      </Archer1>
      <Archer10>
        <X>20</X>
        <Y>12.4</Y>
        <Z>7</Z>
      </Archer10>
      <Archer11>
        <X>-20</X>
        <Y>12.4</Y>
        <Z>-7</Z>
      </Archer11>
      <Archer12>
        <X>-20</X>
        <Y>12.4</Y>
        <Z>7</Z>
      </Archer12>
      <Archer13>
        <X>20</X>
        <Y>12.4</Y>
        <Z>-7</Z>
      </Archer13>
      <Archer2>
        <X>16.3</X>
        <Y>12.4</Y>
        <Z>16.3</Z>
      </Archer2>
      <Archer3>
        <X>-16.3</X>
        <Y>12.4</Y>
        <Z>-16.3</Z>
      </Archer3>
      <Archer4>
        <X>-16.3</X>
        <Y>12.4</Y>
        <Z>16.3</Z>
      </Archer4>
      <Archer5>
        <X>16.3</X>
        <Y>12.4</Y>
        <Z>-16.3</Z>
      </Archer5>
      <Archer6>
        <X>7</X>
        <Y>12.4</Y>
        <Z>20.0</Z>
      </Archer6>
      <Archer7>
        <X>-7</X>
        <Y>12.4</Y>
        <Z>-20.0</Z>
      </Archer7>
      <Archer8>
        <X>-7</X>
        <Y>12.4</Y>
        <Z>20.0</Z>
      </Archer8>
      <Archer9>
        <X>7</X>
        <Y>12.4</Y>
        <Z>-20.0</Z>
      </Archer9>
    </TurretPoints>
  </TurretHolder>
  <VisualActor>
    <Actor>structures/ordona/ordona_garrisonA.xml</Actor>
    <FoundationActor>structures/ordona/ordona_scaffoldA.xml</FoundationActor>
  </VisualActor>
  <WallPiece>
    <Indent>7.6</Indent>
    <Length>50.0</Length>
  </WallPiece>
</Entity>
