<Entity parent="template_unit_hero_infantry_infantry">
  <Attack>
    <Melee>
      <AttackName>Sword</AttackName>
      <Damage>
        <Hack>22.0</Hack>
        <Pierce>7.0</Pierce>
      </Damage>
      <MaxRange>6.0</MaxRange>
      <PreferredClasses datatype="tokens">Infantry Siege</PreferredClasses>
      <PrepareTime>1200</PrepareTime>
      <RepeatTime>1300</RepeatTime>
    </Melee>
  </Attack>
  <Cost>
    <BuildTime>60</BuildTime>
    <Resources>
      <metal>470</metal>
      
      
      
    </Resources>
  </Cost>
  <Footprint>
    <Circle radius="3.0" />
    <Height>5.0</Height>
  </Footprint>
  <Health>
    <Max>2500</Max>
  </Health>
  <Identity>
    <Civ>ordona</Civ>
    <Classes datatype="tokens">HeroColin Hero5 Knight Medium</Classes>
    <GenericName>Squire of Ordon</GenericName>
    <HideIfTechnologyRequirementIsNotMet>true</HideIfTechnologyRequirementIsNotMet>
    <History>The son of Rusl, Colin grew up as a farmhand most of his life. His father instilled in him a love of the sword and was sure to teach him sword, a skill that Colin took on as a profession in his adulthood. He has since become a Squire in hopes of attaining Knighthood.</History>
    <Icon>units/ordona/ord_hero_colin.dds</Icon>
    <Lang>ordona</Lang>
    <RequiredTechnology>civ_choices/ordona/choosehero_colin</RequiredTechnology>
    <SpecificName>Colin</SpecificName>
    <Tooltip>Quick Melee Hero armed with a sword and shield.</Tooltip>
    <VisibleClasses datatype="tokens">Melee</VisibleClasses>
  </Identity>
  <Resistance>
    <Entity>
      <Damage>
        <Crush>30.0</Crush>
        <Fire>10.0</Fire>
        <Forest>10.0</Forest>
        <Hack>40.0</Hack>
        <Light>10.0</Light>
        <Pierce>60.0</Pierce>
        <Shadow>10.0</Shadow>
        <Spirit>10.0</Spirit>
        <Water>10.0</Water>
      </Damage>
    </Entity>
    <KnockbackResistance>100</KnockbackResistance>
  </Resistance>
  <Sound>
    <SoundGroups>
      <attack_melee>attack/weapon/sword.xml</attack_melee>
      <death>voice/ordona/rusl/rusl_death.xml</death>
      <order_attack>voice/ordona/rusl/rusl_attack.xml</order_attack>
      <order_garrison>voice/ordona/rusl/rusl_garrison.xml</order_garrison>
      <order_gather>voice/ordona/rusl/rusl_gather.xml</order_gather>
      <order_repair>voice/ordona/rusl/rusl_repair.xml</order_repair>
      <order_walk>voice/ordona/rusl/rusl_walk.xml</order_walk>
      <run>actor/human/movement/walk.xml</run>
      <select>voice/ordona/rusl/rusl_select.xml</select>
      <trained>interface/alarm/alarm_create_hero.xml</trained>
      <walk>actor/human/movement/walk.xml</walk>
    </SoundGroups>
  </Sound>
  <TrainingRestrictions>
    <Category>Hero5</Category>
  </TrainingRestrictions>
  <VisualActor>
    <Actor>units/ordona/ordona_hero_colin_b.xml</Actor>
  </VisualActor>
</Entity>
